src/__init__.py
src/clean_md.py
src/clean_unnecessary_data.py
src/download_with_media.py
src/html_to_md.py
src/main.py
src/url_to_local.py
medium2md-2.0.0.dist-info/LICENSE.txt
medium2md-2.0.0.dist-info/METADATA
medium2md-2.0.0.dist-info/WHEEL
medium2md-2.0.0.dist-info/entry_points.txt
medium2md-2.0.0.dist-info/top_level.txt
medium2md-2.0.0.dist-info/RECORD
