Metadata-Version: 2.1
Name: medium2md
Version: 2.0.0
Summary: Download and convert Medium articles to markdown with images
Home-page: https://github.com/siddharthksah/medium2md
Author: Siddharth Kumar
Author-email: siddharth123sk@gmail.com
Project-URL: Bug Tracker, https://github.com/siddharthksah/medium2md/issues
Project-URL: Documentation, https://github.com/siddharthksah/medium2md#readme
Project-URL: Source Code, https://github.com/siddharthksah/medium2md
Classifier: Development Status :: 5 - Production/Stable
Classifier: Intended Audience :: Developers
Classifier: License :: OSI Approved :: MIT License
Classifier: Operating System :: OS Independent
Classifier: Programming Language :: Python :: 3
Classifier: Programming Language :: Python :: 3.8
Classifier: Programming Language :: Python :: 3.9
Classifier: Topic :: Text Processing
Classifier: Topic :: Utilities
Requires-Python: >=3.8
License-File: LICENSE.txt
Requires-Dist: beautifulsoup4 (==4.12.2)
Requires-Dist: certifi (==2023.7.22)
Requires-Dist: chardet (==5.1.0)
Requires-Dist: charset-normalizer (==3.2.0)
Requires-Dist: colorama (==0.4.6)
Requires-Dist: cssselect (==1.2.0)
Requires-Dist: greenlet (==2.0.2)
Requires-Dist: html2text (==2020.1.16)
Requires-Dist: idna (==3.4)
Requires-Dist: lxml (==4.9.3)
Requires-Dist: playwright (==1.36.0)
Requires-Dist: pyee (==9.0.4)
Requires-Dist: pyfiglet (==0.8.post1)
Requires-Dist: PyInquirer (==1.0.3)
Requires-Dist: readability-lxml (==0.8.1)
Requires-Dist: requests (==2.31.0)
Requires-Dist: setuptools (==67.8.0)
Requires-Dist: soupsieve (==2.4.1)
Requires-Dist: termcolor (==2.3.0)
Requires-Dist: tqdm (==4.65.0)
Requires-Dist: typing-extensions (==4.7.1)
Requires-Dist: urllib3 (==2.0.4)
Requires-Dist: wheel (==0.38.4)
